kwpbar/__init__.py
kwpbar/demo.py
kwpbar-0.2.1.dist-info/METADATA
kwpbar-0.2.1.dist-info/RECORD
kwpbar-0.2.1.dist-info/WHEEL
kwpbar-0.2.1.dist-info/top_level.txt
